devopness_mcp_server/README.md
devopness_mcp_server/__init__.py
devopness_mcp_server/main.py
devopness_mcp_server/py.typed
devopness_mcp_server/server.py
devopness_mcp_server/lib/__init__.py
devopness_mcp_server/lib/devopness_api.py
devopness_mcp_server/lib/environment.py
devopness_mcp_server/lib/models.py
devopness_mcp_server/lib/patch.py
devopness_mcp_server/lib/response.py
devopness_mcp_server/lib/token_verifier.py
devopness_mcp_server/lib/tools.py
devopness_mcp_server/lib/types.py
devopness_mcp_server/lib/utils.py
devopness_mcp_server/lib/middlewares/__init__.py
devopness_mcp_server/lib/middlewares/auth_middleware.py
devopness_mcp_server/lib/services/action_service.py
devopness_mcp_server/lib/services/application_service.py
devopness_mcp_server/lib/services/credential_service.py
devopness_mcp_server/lib/services/daemon_service.py
devopness_mcp_server/lib/services/environment_service.py
devopness_mcp_server/lib/services/network_rule_service.py
devopness_mcp_server/lib/services/network_service.py
devopness_mcp_server/lib/services/pipeline_service.py
devopness_mcp_server/lib/services/project_service.py
devopness_mcp_server/lib/services/server_service.py
devopness_mcp_server/lib/services/service_service.py
devopness_mcp_server/lib/services/ssh_key_service.py
devopness_mcp_server/lib/services/ssl_certificate.py
devopness_mcp_server/lib/services/user_service.py
devopness_mcp_server/lib/services/virtual_host_service.py
devopness_mcp_server/lib/services/webhook_service.py
devopness_mcp_server-0.0.41.dist-info/METADATA
devopness_mcp_server-0.0.41.dist-info/WHEEL
devopness_mcp_server-0.0.41.dist-info/entry_points.txt
devopness_mcp_server-0.0.41.dist-info/RECORD
